yua_compressor/__init__.py
yua_compressor/__main__.py
yua_compressor/core.py
yua_compressor-0.1.3.dist-info/licenses/LICENSE
yua_compressor-0.1.3.dist-info/METADATA
yua_compressor-0.1.3.dist-info/WHEEL
yua_compressor-0.1.3.dist-info/entry_points.txt
yua_compressor-0.1.3.dist-info/top_level.txt
yua_compressor-0.1.3.dist-info/RECORD
