Metadata-Version: 2.4
Name: yua-compressor
Version: 0.1.3
Summary: YUA Compressor: custom compression format with optional AES-GCM encryption (zlib/zstd)
Author-email: 結愛ちゃん <nakamurakensuke5@gmail.com>
License: MIT
Project-URL: Homepage, https://example.com/yua-compressor
Project-URL: Repository, https://example.com/yua-compressor
Keywords: compression,zstd,zlib,encryption,AES-GCM,archive,cli
Classifier: Programming Language :: Python :: 3
Classifier: License :: OSI Approved :: MIT License
Classifier: Operating System :: OS Independent
Requires-Python: >=3.9
License-File: LICENSE
Requires-Dist: cryptography>=42.0.0
Provides-Extra: zstd
Requires-Dist: zstandard>=0.22.0; extra == "zstd"
Dynamic: license-file
